odoo8_addon_invoice_margin-8.0.1.0.0-py2.7-nspkg.pth
odoo8_addon_invoice_margin-8.0.1.0.0.dist-info/DESCRIPTION.rst
odoo8_addon_invoice_margin-8.0.1.0.0.dist-info/METADATA
odoo8_addon_invoice_margin-8.0.1.0.0.dist-info/RECORD
odoo8_addon_invoice_margin-8.0.1.0.0.dist-info/WHEEL
odoo8_addon_invoice_margin-8.0.1.0.0.dist-info/metadata.json
odoo8_addon_invoice_margin-8.0.1.0.0.dist-info/namespace_packages.txt
odoo8_addon_invoice_margin-8.0.1.0.0.dist-info/top_level.txt
odoo_addons/invoice_margin/README.rst
odoo_addons/invoice_margin/__init__.py
odoo_addons/invoice_margin/__openerp__.py
odoo_addons/invoice_margin/i18n/fr.po
odoo_addons/invoice_margin/models/__init__.py
odoo_addons/invoice_margin/models/account_invoice.py
odoo_addons/invoice_margin/models/account_invoice_line.py
odoo_addons/invoice_margin/static/description/account_invoice_form.png
odoo_addons/invoice_margin/views/view_account_invoice.xml
